qetoo2/__init__.py
qetoo2/core.py
qetoo-0.1.0.dist-info/METADATA
qetoo-0.1.0.dist-info/WHEEL
qetoo-0.1.0.dist-info/top_level.txt
qetoo-0.1.0.dist-info/RECORD
