Metadata-Version: 2.4
Name: qetoo
Version: 0.1.0
Summary: Simple browser opening helper
Author: YourName
Requires-Python: >=3.8
Requires-Dist: playwright
